{"messagesRecieved":400464,"ban":{"uses":5,"lastUsed":1597281443327},"buy":{"uses":270,"lastUsed":1597596941649},"coin":{"uses":51,"lastUsed":1597510099320},"crab":{"uses":298,"lastUsed":1597596946974},"daily":{"uses":111,"lastUsed":1597599058992},"deposit":{"uses":37,"lastUsed":1597593790754},"embed":{"uses":0,"lastUsed":0},"fish":{"uses":334,"lastUsed":1597596878058},"help":{"uses":99,"lastUsed":1597596338241},"hunt":{"uses":541,"lastUsed":1597599063857},"inventory":{"uses":136,"lastUsed":1597596913284},"invite":{"uses":22,"lastUsed":1597593694328},"kick":{"uses":3,"lastUsed":1597281657713},"leaderboard":{"uses":126,"lastUsed":1597596352672},"math":{"uses":23,"lastUsed":1597594036303},"money":{"uses":326,"lastUsed":1597599070046},"pet":{"uses":287,"lastUsed":1597596343503},"phrase":{"uses":3,"lastUsed":1597291252090},"profile":{"uses":90,"lastUsed":1597596315421},"purge":{"uses":80,"lastUsed":1597597228226},"race":{"uses":19,"lastUsed":1597590330666},"reload":{"uses":75,"lastUsed":1597589476115},"rob":{"uses":22,"lastUsed":1597358899842},"rps":{"uses":66,"lastUsed":1597508836763},"search":{"uses":475,"lastUsed":1597596905138},"send":{"uses":4,"lastUsed":1594933072763},"shop":{"uses":100,"lastUsed":1597594541111},"stats":{"uses":62,"lastUsed":1597522433518},"sudo":{"uses":67,"lastUsed":1597599078750},"use":{"uses":34,"lastUsed":1597503136605},"version":{"uses":3,"lastUsed":1595369389881},"withdraw":{"uses":26,"lastUsed":1597593839707},"work":{"uses":139,"lastUsed":1597599060261},"report":{"uses":9,"lastUsed":1594143252664},"give":{"uses":2,"lastUsed":1597361208155},"specialShop":{"uses":0,"lastUsed":0},"specialshop":{"uses":12,"lastUsed":1597594094906},"sell":{"uses":162,"lastUsed":1597596930425},"chop":{"uses":157,"lastUsed":1597598480350},"craft":{"uses":312,"lastUsed":1597598482184},"explore":{"uses":107,"lastUsed":1597598485739},"farm":{"uses":126,"lastUsed":1597593897302},"mine":{"uses":205,"lastUsed":1597596923824},"raid":{"uses":98,"lastUsed":1597596894153},"music":{"uses":9,"lastUsed":1594073533621},"team":{"uses":89,"lastUsed":1597594253192},"achievements":{"uses":1,"lastUsed":1597594273972},"title":{"uses":31,"lastUsed":1597594694270},"code":{"uses":18,"lastUsed":1597594061134},"vote":{"uses":3,"lastUsed":1595782558996}}