{"ban":{"uses":8,"lastUsed":1608162054117},"buy":{"uses":1050,"lastUsed":1608751112905},"coin":{"uses":201,"lastUsed":1606264248334},"crab":{"uses":934,"lastUsed":1608751115531},"daily":{"uses":644,"lastUsed":1608751066674},"deposit":{"uses":158,"lastUsed":1608137135769},"embed":{"uses":13,"lastUsed":1603336344809},"fish":{"uses":963,"lastUsed":1608751116809},"help":{"uses":303,"lastUsed":1608601035399},"hunt":{"uses":1234,"lastUsed":1608744625611},"inventory":{"uses":830,"lastUsed":1608743549834},"invite":{"uses":34,"lastUsed":1608231997568},"kick":{"uses":4,"lastUsed":1608162033568},"leaderboard":{"uses":320,"lastUsed":1608667081769},"math":{"uses":192,"lastUsed":1608595908368},"money":{"uses":1277,"lastUsed":1608751123677},"pet":{"uses":1165,"lastUsed":1608702137929},"phrase":{"uses":13,"lastUsed":1603748768997},"profile":{"uses":417,"lastUsed":1608751147743},"purge":{"uses":243,"lastUsed":1608589859051},"race":{"uses":55,"lastUsed":1604283426563},"reload":{"uses":248,"lastUsed":1608749981038},"rob":{"uses":59,"lastUsed":1608596337606},"rps":{"uses":87,"lastUsed":1606158476563},"search":{"uses":1038,"lastUsed":1608595885973},"send":{"uses":17,"lastUsed":1602277771981},"shop":{"uses":422,"lastUsed":1608595840568},"stats":{"uses":83,"lastUsed":1608578772938},"sudo":{"uses":99,"lastUsed":1603746974237},"use":{"uses":136,"lastUsed":1608137212841},"version":{"uses":7,"lastUsed":1598801883976},"withdraw":{"uses":412,"lastUsed":1608751062947},"work":{"uses":780,"lastUsed":1608751068044},"report":{"uses":10,"lastUsed":1600528943638},"give":{"uses":22,"lastUsed":1608751076961},"specialShop":{"uses":0,"lastUsed":0},"specialshop":{"uses":44,"lastUsed":1608589838998},"sell":{"uses":599,"lastUsed":1608231812761},"chop":{"uses":692,"lastUsed":1608751074398},"craft":{"uses":857,"lastUsed":1608743555576},"explore":{"uses":469,"lastUsed":1608595375375},"farm":{"uses":993,"lastUsed":1608751079926},"mine":{"uses":918,"lastUsed":1608751121593},"raid":{"uses":486,"lastUsed":1608744628409},"music":{"uses":9,"lastUsed":1594073533621},"team":{"uses":133,"lastUsed":1603587038390},"achievements":{"uses":19,"lastUsed":1603291875082},"title":{"uses":84,"lastUsed":1606264178671},"code":{"uses":41,"lastUsed":1608254362777},"vote":{"uses":68,"lastUsed":1608657016878},"addMoney":{"uses":0,"lastUsed":0},"removeMoney":{"uses":0,"lastUsed":0},"addmoney":{"uses":17,"lastUsed":1608137391327},"removemoney":{"uses":2,"lastUsed":1606333813617},"deop":{"uses":29,"lastUsed":1605065100797},"op":{"uses":44,"lastUsed":1608153269724},"setusertype":{"uses":4,"lastUsed":1599235972863},"make":{"uses":636,"lastUsed":1608751082948},"setmoney":{"uses":29,"lastUsed":1608093028887},"house":{"uses":186,"lastUsed":1608223356915},"getobject":{"uses":11,"lastUsed":1603251756421},"loan":{"uses":53,"lastUsed":1603922923674},"delwarn":{"uses":5,"lastUsed":1603489179585},"warn":{"uses":5,"lastUsed":1606351945818},"warnings":{"uses":17,"lastUsed":1603740864337},"settings":{"uses":51,"lastUsed":1608093451176},"study":{"uses":32,"lastUsed":1604862563477},"fight":{"uses":52,"lastUsed":1604623639758},"workout":{"uses":144,"lastUsed":1608657574684},"test":{"uses":11,"lastUsed":1604942371262},"slowmode":{"uses":17,"lastUsed":1606701821412},"advancements":{"uses":72,"lastUsed":1608750943593},"guess":{"uses":10,"lastUsed":1606596128280},"perms":{"uses":23,"lastUsed":1606156543759},"backup":{"uses":29,"lastUsed":1608590123128},"serverinfo":{"uses":7,"lastUsed":1608161084481},"rules":{"uses":3,"lastUsed":1608093220215},"keyargs":{"uses":4,"lastUsed":1608232879199},"emoji":{"uses":3,"lastUsed":1608310953978},"quest":{"uses":89,"lastUsed":1608750910471},"moneylog":{"uses":3,"lastUsed":1608751080143}}