{"509874745567870987":{"cash":5604448,"bank":431354,"gems":16,"xp":60,"xpUntil":610,"level":15,"inventory":{"gold":{"amount":2,"uses":1},"lock":{"amount":0,"uses":1},"carrot":{"amount":128,"uses":1},"knife":{"amount":0,"uses":1},"glass":{"amount":0,"uses":1},"string":{"amount":2,"uses":1},"coin":{"amount":255,"uses":1},"magnif":{"amount":41,"uses":1},"fishingrod":{"amount":78,"uses":8},"cage":{"amount":0,"uses":10},"craftingbench":{"amount":2,"uses":1},"goldenbook":{"amount":0,"uses":1},"gloves":{"amount":1,"uses":4},"dumbbell":{"amount":1,"uses":1},"shoes":{"amount":1,"uses":2},"axe":{"amount":1,"uses":9},"wood":{"amount":4,"uses":1},"pickaxe":{"amount":1,"uses":14},"iron":{"amount":3,"uses":1},"healthpot":{"amount":0,"uses":1}},"username":"wsquarepa","account":{"secured":false,"type":"admin","daily":{"streak":4,"previousAmt":133,"expires":1600399376680},"title":"Da Rich Dood"},"pet":{"food":0,"coins":7702,"type":"human","name":"Willy"},"team":"","achivements":["Get more than $100000 in cash","Get 1 Million blubbadoo bux!","Store $10000 into the bank","Craft something"],"codesUsed":[],"nextVoteTime":1599543050467,"nextGemCashGoal":10992378,"<@!509874745567870987>":null,"houses":[{"durability":997523,"level":6,"xp":775,"xpUntil":1270},{"durability":997525,"level":6,"xp":773,"xpUntil":1270},{"durability":998949,"level":2,"xp":347,"xpUntil":400}],"loan":{},"intellegencePoints":3,"strength":4,"defence":1,"maxHP":150,"hp":150},"346322816754253825":{"cash":1667,"bank":0,"gems":3,"xp":0,"xpUntil":40,"level":3,"inventory":{"knife":{"amount":0,"uses":1},"carrot":{"amount":0,"uses":1},"fishingrod":{"amount":1,"uses":9},"pickaxe":{"amount":1,"uses":14},"iron":{"amount":1,"uses":1},"gold":{"amount":1,"uses":1}},"username":"0x41*32","account":{"secured":false,"type":"user","daily":{"streak":-1,"previousAmt":0,"expires":1598318622664},"title":"none"},"pet":{},"team":"","achivements":[],"codesUsed":[],"nextVoteTime":0,"nextGemCashGoal":5000,"houses":[],"loan":{}},"737465978522173441":{"cash":111046,"bank":0,"gems":15,"xp":235,"xpUntil":340,"level":11,"inventory":{"craftingbench":{"amount":1,"uses":1},"knife":{"amount":5,"uses":1},"fishingrod":{"amount":1,"uses":4},"cage":{"amount":1,"uses":4},"carrot":{"amount":603,"uses":1},"axe":{"amount":2,"uses":4},"wood":{"amount":44,"uses":1},"pickaxe":{"amount":1,"uses":12},"map":{"amount":13,"uses":1},"magnif":{"amount":6,"uses":1},"chest":{"amount":0,"uses":1},"key":{"amount":0,"uses":1},"glass":{"amount":8,"uses":1},"string":{"amount":21,"uses":1},"iron":{"amount":31,"uses":1},"gold":{"amount":6,"uses":1},"coin":{"amount":9,"uses":1},"lock":{"amount":1,"uses":1}},"username":"pieceofgrass","account":{"secured":false,"type":"user","daily":{"streak":2,"previousAmt":48,"expires":1598631329309},"title":"Da Rich Dood"},"pet":{"food":0,"coins":0,"type":"Poseidon","name":"OOF Andy"},"team":"","achivements":["Craft something","Store $10000 into the bank","Get more than $100000 in cash"],"codesUsed":[],"nextVoteTime":1598532142226,"nextGemCashGoal":123784,"houses":[],"loan":{},"intellegencePoints":1,"strength":0,"defence":0,"maxHP":100,"hp":100},"703336679888650371":{"cash":784741,"bank":0,"gems":76,"xp":50,"xpUntil":610,"level":15,"inventory":{"carrot":{"amount":1480,"uses":1},"knife":{"amount":6,"uses":1},"lock":{"amount":2,"uses":1},"axe":{"amount":1,"uses":4},"pickaxe":{"amount":2,"uses":13},"wood":{"amount":218,"uses":1},"iron":{"amount":177,"uses":1},"gold":{"amount":0,"uses":1},"craftingbench":{"amount":1,"uses":1},"glass":{"amount":48,"uses":1},"string":{"amount":74,"uses":1},"cage":{"amount":1,"uses":1},"fishingrod":{"amount":1,"uses":1},"magnif":{"amount":2,"uses":1},"moneydoubler":{"amount":0,"uses":1},"map":{"amount":0,"uses":1},"key":{"amount":0,"uses":1},"gloves":{"amount":0,"uses":5},"dumbbell":{"amount":0,"uses":5}},"username":"Velocity","account":{"secured":true,"type":"user","daily":{"streak":29,"previousAmt":6299,"expires":1600797914660},"title":"Millionaire"},"pet":{"food":310,"coins":2966,"type":"Fish 🐟","name":"Fishy"},"team":"","achivements":["Store $10000 into the bank","Craft something","Get more than $100000 in cash","Get 1 Million blubbadoo bux!","Report something"],"codesUsed":["pAcIfIc_AcAdEmY","_9uecVbR","SeCrEtE_cOdE"],"nextVoteTime":1600677377700,"nextGemCashGoal":5010009,"houses":[],"loan":{},"intellegencePoints":1,"strength":5,"defence":5,"maxHP":100,"hp":100},"497869249549828119":{"cash":587793,"bank":0,"gems":20,"xp":286,"xpUntil":400,"level":12,"inventory":{"carrot":{"amount":301,"uses":1},"magnif":{"amount":1,"uses":1},"knife":{"amount":0,"uses":1},"cage":{"amount":0,"uses":10},"map":{"amount":0,"uses":1},"glass":{"amount":13,"uses":1},"string":{"amount":3,"uses":1},"craftingbench":{"amount":1,"uses":1},"axe":{"amount":0,"uses":10},"wood":{"amount":14,"uses":1},"fishingrod":{"amount":0,"uses":10},"chest":{"amount":0,"uses":1},"key":{"amount":0,"uses":1},"lock":{"amount":0,"uses":1},"pickaxe":{"amount":0,"uses":15},"iron":{"amount":14,"uses":1},"gold":{"amount":0,"uses":1},"goldenbook":{"amount":0,"uses":1},"dumbbell":{"amount":0,"uses":5},"shoes":{"amount":1,"uses":3}},"username":"deerpaw","account":{"secured":true,"type":"user","daily":{"streak":20,"previousAmt":2924,"expires":1600801204213},"title":"Hackr"},"pet":{"food":138,"coins":159,"type":"cat🐈","name":"Meowowowowow"},"team":"","achivements":["Craft something","Store $10000 into the bank","Get more than $100000 in cash"],"codesUsed":["pAcIfIc_AcAdEmY","_9uecVbR"],"nextVoteTime":0,"nextGemCashGoal":614118,"houses":[],"loan":{},"intellegencePoints":4,"strength":5,"defence":0,"maxHP":107,"hp":107},"723663758504755321":{"cash":69691,"bank":0,"gems":15,"xp":774,"xpUntil":775,"level":17,"inventory":{"craftingbench":{"amount":1,"uses":1},"fishingrod":{"amount":1,"uses":5},"cage":{"amount":1,"uses":5},"knife":{"amount":0,"uses":1},"carrot":{"amount":160,"uses":1}},"username":"mOnKeY🐵pEePs(•-•)","account":{"secured":false,"type":"user","daily":{"streak":0,"previousAmt":0,"expires":1600648959063},"title":"none"},"pet":{"food":385,"coins":1794,"type":"blubb","name":"pet pet"},"team":"","achivements":["Craft something"],"codesUsed":[],"nextVoteTime":0,"nextGemCashGoal":130114,"houses":[],"loan":{},"intellegencePoints":1,"strength":0,"defence":0,"maxHP":100,"hp":100},"705277675308318751":{"cash":41300,"bank":0,"gems":23,"xp":329,"xpUntil":775,"level":17,"inventory":{"fishingrod":{"amount":1,"uses":4},"cage":{"amount":1,"uses":5},"knife":{"amount":0,"uses":1},"magnif":{"amount":0,"uses":1},"map":{"amount":0,"uses":1},"axe":{"amount":1,"uses":7},"wood":{"amount":10,"uses":1},"craftingbench":{"amount":1,"uses":1},"pickaxe":{"amount":1,"uses":12},"iron":{"amount":2,"uses":1},"carrot":{"amount":0,"uses":1},"glass":{"amount":7,"uses":1},"string":{"amount":2,"uses":1},"dumbbell":{"amount":1,"uses":4}},"username":"CARAT","account":{"secured":false,"type":"user","daily":{"streak":0,"previousAmt":0,"expires":1600648952954},"title":"Blacksmith"},"pet":{},"team":"","achivements":["Craft something"],"codesUsed":[],"nextVoteTime":0,"nextGemCashGoal":117088,"houses":[],"loan":{},"intellegencePoints":1,"strength":1,"defence":0,"maxHP":100,"hp":100},"738483215156772874":{"cash":704022,"bank":0,"gems":38,"xp":937,"xpUntil":1165,"level":21,"inventory":{"carrot":{"amount":280,"uses":1},"knife":{"amount":3,"uses":1},"glass":{"amount":75,"uses":1},"string":{"amount":75,"uses":1},"magnif":{"amount":0,"uses":1},"fishingrod":{"amount":1,"uses":3},"craftingbench":{"amount":2,"uses":1},"axe":{"amount":2,"uses":7},"wood":{"amount":50,"uses":1},"pickaxe":{"amount":1,"uses":12},"iron":{"amount":60,"uses":1},"gold":{"amount":0,"uses":1},"cage":{"amount":1,"uses":4},"coin":{"amount":0,"uses":1},"lock":{"amount":3,"uses":1},"map":{"amount":1,"uses":1},"key":{"amount":1,"uses":1},"chest":{"amount":0,"uses":1},"moneydoubler":{"amount":0,"uses":1},"goldenbook":{"amount":0,"uses":1},"dumbbell":{"amount":0,"uses":5}},"username":"DA POTATO!","account":{"secured":true,"type":"user","daily":{"streak":4,"previousAmt":125,"expires":1600801555753},"title":"Millionaire"},"pet":{"food":26,"coins":845,"type":"Zeus, King of the Gods!","name":"MY PET POTATO"},"team":"","achivements":["Craft something","Store $10000 into the bank","Get more than $100000 in cash","Get 1 Million blubbadoo bux!"],"codesUsed":[],"nextVoteTime":1598679820306,"nextGemCashGoal":3360781,"houses":[],"loan":{},"intellegencePoints":3,"strength":20,"defence":0,"maxHP":100,"hp":100},"690666742271180832":{"cash":60724,"bank":0,"gems":19,"xp":551,"xpUntil":775,"level":17,"inventory":{},"username":"EmeraldPickles","account":{"secured":false,"type":"user","daily":{"streak":-1,"previousAmt":0,"expires":1598329995589},"title":"none"},"pet":{},"team":"","achivements":[],"codesUsed":[],"nextVoteTime":0,"nextGemCashGoal":65046,"houses":[],"loan":{},"intellegencePoints":1,"strength":0,"defence":0,"maxHP":100,"hp":100},"663626013749805066":{"cash":0,"bank":0,"gems":0,"xp":1,"xpUntil":10,"level":0,"inventory":{},"username":"Cheems, the thermonuclear dog","account":{"secured":false,"type":"user","daily":{"streak":-1,"previousAmt":0,"expires":1598332328537},"title":"none"},"pet":{},"team":"","achivements":[],"codesUsed":[],"nextVoteTime":0,"nextGemCashGoal":5000,"loan":{},"houses":[]},"536659745420083208":{"cash":1630,"bank":0,"gems":3,"xp":18,"xpUntil":85,"level":5,"inventory":{"knife":{"amount":1,"uses":1}},"username":"ｔｒｏｌｌｌｅｎｎｙ","account":{"secured":false,"type":"user","daily":{"streak":0,"previousAmt":0,"expires":1600487496795},"title":"Hackr"},"pet":{},"team":"","achivements":[],"codesUsed":["_9uecVbR"],"nextVoteTime":0,"nextGemCashGoal":5000,"houses":[],"loan":{},"intellegencePoints":1,"strength":0,"defence":0,"maxHP":100,"hp":100},"716336552346910721":{"cash":17,"bank":0,"gems":1,"xp":0,"xpUntil":25,"level":2,"inventory":{},"username":"₉⁹₉ Jay ₉⁹₉","account":{"secured":false,"type":"user","daily":{"streak":-1,"previousAmt":0,"expires":1598422270628},"title":"none"},"pet":{},"team":"","achivements":[],"codesUsed":[],"nextVoteTime":0,"nextGemCashGoal":5000,"loan":{},"houses":[],"intellegencePoints":1,"strength":0,"defence":0,"maxHP":100,"hp":100},"672882686552965161":{"cash":9,"bank":0,"gems":0,"xp":8,"xpUntil":15,"level":1,"inventory":{},"username":"HazeCobra","account":{"secured":false,"type":"user","daily":{"streak":-1,"previousAmt":0,"expires":1598426888616},"title":"none"},"pet":{},"team":"","achivements":[],"codesUsed":[],"nextVoteTime":0,"nextGemCashGoal":5000,"houses":[],"loan":{}},"631084070419300373":{"cash":0,"bank":0,"gems":0,"xp":3,"xpUntil":10,"level":0,"inventory":{},"username":"Haze.Spoonfish","account":{"secured":false,"type":"user","daily":{"streak":-1,"previousAmt":0,"expires":1598441070981},"title":"none"},"pet":{},"team":"","achivements":[],"codesUsed":[],"nextVoteTime":0,"nextGemCashGoal":5000,"houses":[],"loan":{},"intellegencePoints":1,"strength":0,"defence":0,"maxHP":100,"hp":100},"657224775088996353":{"cash":0,"bank":0,"gems":0,"xp":3,"xpUntil":10,"level":0,"inventory":{},"username":"İsmaiLYusufYldrM","account":{"secured":false,"type":"user","daily":{"streak":-1,"previousAmt":0,"expires":1598451012510},"title":"none"},"pet":{},"team":"","achivements":[],"codesUsed":[],"nextVoteTime":0,"nextGemCashGoal":5000,"loan":{},"houses":[]},"539272433853661204":{"cash":3,"bank":0,"gems":1,"xp":2,"xpUntil":15,"level":1,"inventory":{},"username":"debbie.","account":{"secured":false,"type":"user","daily":{"streak":-1,"previousAmt":0,"expires":1598458127991},"title":"none"},"pet":{},"team":"","achivements":[],"codesUsed":[],"nextVoteTime":0,"nextGemCashGoal":5000,"houses":[],"loan":{},"intellegencePoints":1,"strength":0,"defence":0,"maxHP":100,"hp":100},"675426268556165130":{"cash":9,"bank":0,"gems":0,"xp":8,"xpUntil":15,"level":1,"inventory":{},"username":"彼キラですか？","account":{"secured":false,"type":"user","daily":{"streak":-1,"previousAmt":0,"expires":1598462156520},"title":"none"},"pet":{},"team":"","achivements":[],"codesUsed":[],"nextVoteTime":0,"nextGemCashGoal":5000,"houses":[],"loan":{},"intellegencePoints":1},"629653252996333590":{"cash":0,"bank":0,"gems":0,"xp":2,"xpUntil":10,"level":0,"inventory":{},"username":"Haze.death","account":{"secured":false,"type":"user","daily":{"streak":-1,"previousAmt":0,"expires":1598466525417},"title":"none"},"pet":{},"team":"","achivements":[],"codesUsed":[],"nextVoteTime":0,"nextGemCashGoal":5000,"loan":{},"houses":[],"intellegencePoints":1,"strength":0,"defence":0,"maxHP":100,"hp":100},"706231452001370223":{"cash":0,"bank":0,"gems":0,"xp":7,"xpUntil":10,"level":0,"inventory":{},"username":"!!","account":{"secured":false,"type":"user","daily":{"streak":-1,"previousAmt":0,"expires":1598468926349},"title":"none"},"pet":{},"team":"","achivements":[],"codesUsed":[],"nextVoteTime":0,"nextGemCashGoal":5000,"houses":[],"loan":{},"intellegencePoints":1,"strength":0,"defence":0,"maxHP":100,"hp":100},"588045302330687559":{"cash":0,"bank":0,"gems":0,"xp":4,"xpUntil":10,"level":0,"inventory":{},"username":"leonard","account":{"secured":false,"type":"user","daily":{"streak":-1,"previousAmt":0,"expires":1598469189921},"title":"none"},"pet":{},"team":"","achivements":[],"codesUsed":[],"nextVoteTime":0,"nextGemCashGoal":5000,"loan":{},"houses":[]},"747546437822185495":{"cash":3262,"bank":0,"gems":2,"xp":17,"xpUntil":60,"level":4,"inventory":{"carrot":{"amount":0,"uses":1},"coin":{"amount":1,"uses":1}},"username":"Psycopathic Chicken Boi!","account":{"secured":false,"type":"user","daily":{"streak":0,"previousAmt":0,"expires":1598559633579},"title":"none"},"pet":{},"team":"","achivements":[],"codesUsed":[],"nextVoteTime":0,"nextGemCashGoal":5000,"houses":[],"loan":{},"intellegencePoints":1},"695817483281760257":{"cash":1877,"bank":0,"gems":3,"xp":104,"xpUntil":115,"level":6,"inventory":{},"username":"Ramen_Panda_UwU","account":{"secured":false,"type":"user","daily":{"streak":-1,"previousAmt":0,"expires":1598472567324},"title":"none"},"pet":{},"team":"","achivements":[],"codesUsed":[],"nextVoteTime":0,"nextGemCashGoal":5000,"houses":[],"loan":{},"intellegencePoints":1,"strength":0,"defence":0,"maxHP":100,"hp":100},"698281285596217475":{"cash":42,"bank":10879,"gems":5,"xp":77,"xpUntil":150,"level":7,"inventory":{"knife":{"amount":1,"uses":1},"glass":{"amount":33,"uses":1},"string":{"amount":61,"uses":1},"map":{"amount":7,"uses":1},"cage":{"amount":1,"uses":8},"magnif":{"amount":4,"uses":1},"pickaxe":{"amount":1,"uses":4},"iron":{"amount":15,"uses":1},"fishingrod":{"amount":1,"uses":8},"craftingbench":{"amount":2,"uses":1},"coin":{"amount":0,"uses":1},"carrot":{"amount":444,"uses":1},"wood":{"amount":18,"uses":1},"gold":{"amount":8,"uses":1},"axe":{"amount":1,"uses":3}},"username":"AdriYEET","account":{"secured":false,"type":"user","daily":{"streak":1,"previousAmt":18,"expires":1598742051218},"title":"I want my money safe"},"pet":{"food":341,"coins":494,"type":"Demon","name":"666"},"team":"","achivements":["Craft something","Store $10000 into the bank"],"codesUsed":[],"nextVoteTime":0,"nextGemCashGoal":15481,"houses":[],"loan":{}},"630797206726639616":{"cash":0,"bank":0,"gems":0,"xp":1,"xpUntil":10,"level":0,"inventory":{},"username":"HazeMaddMatt","account":{"secured":false,"type":"user","daily":{"streak":-1,"previousAmt":0,"expires":1598638849119},"title":""},"pet":{},"team":"","achivements":[],"codesUsed":[],"nextVoteTime":0,"nextGemCashGoal":5000,"loan":{},"houses":[]},"352215542679207946":{"cash":5,"bank":0,"gems":1,"xp":4,"xpUntil":15,"level":1,"inventory":{},"username":"Stuff and Magic 2","account":{"secured":false,"type":"user","daily":{"streak":-1,"previousAmt":0,"expires":1598651513300},"title":"none"},"pet":{},"team":"","achivements":[],"codesUsed":[],"nextVoteTime":0,"nextGemCashGoal":5000,"houses":[],"loan":{},"intellegencePoints":1},"736956906001924198":{"cash":0,"bank":0,"gems":0,"xp":4,"xpUntil":10,"level":0,"inventory":{},"username":"Sentinal9K","account":{"secured":false,"type":"user","daily":{"streak":-1,"previousAmt":0,"expires":1598656479344},"title":""},"pet":{},"team":"","achivements":[],"codesUsed":[],"nextVoteTime":0,"nextGemCashGoal":5000,"loan":{},"houses":[]},"641082474830495774":{"cash":0,"bank":56215,"gems":13,"xp":38,"xpUntil":235,"level":9,"inventory":{"knife":{"amount":28,"uses":1},"fishingrod":{"amount":1,"uses":1},"magnif":{"amount":0,"uses":1},"cage":{"amount":1,"uses":1},"wood":{"amount":20,"uses":1},"craftingbench":{"amount":2,"uses":1},"iron":{"amount":21,"uses":1},"map":{"amount":8,"uses":1},"glass":{"amount":72,"uses":1},"string":{"amount":95,"uses":1},"chest":{"amount":0,"uses":1},"key":{"amount":1,"uses":1},"carrot":{"amount":0,"uses":1},"lock":{"amount":0,"uses":1},"dumbbell":{"amount":0,"uses":5},"gloves":{"amount":0,"uses":5},"axe":{"amount":1,"uses":4},"pickaxe":{"amount":1,"uses":9},"gold":{"amount":6,"uses":1}},"username":"Alynn","account":{"secured":true,"type":"user","daily":{"streak":0,"previousAmt":0,"expires":1600745266536},"title":"I want my money safe"},"pet":{"food":115,"coins":353,"type":"","name":"pet"},"team":"","achivements":["Craft something","Store $10000 into the bank"],"codesUsed":[],"nextVoteTime":0,"nextGemCashGoal":64523,"houses":[],"loan":{},"intellegencePoints":1,"strength":5,"defence":5,"maxHP":100,"hp":100},"637055205560680478":{"cash":0,"bank":0,"gems":0,"xp":3,"xpUntil":10,"level":0,"inventory":{},"username":"Maximilien Robespierre","account":{"secured":false,"type":"user","daily":{"streak":-1,"previousAmt":0,"expires":1598706559828},"title":""},"pet":{},"team":"","achivements":[],"codesUsed":[],"nextVoteTime":0,"nextGemCashGoal":5000,"loan":{},"houses":[]},"687675453045080125":{"cash":0,"bank":0,"gems":0,"xp":2,"xpUntil":10,"level":0,"inventory":{},"username":"[𝓢𝓒]𝓔𝓷𝓮𝓻𝓰𝔂","account":{"secured":false,"type":"user","daily":{"streak":-1,"previousAmt":0,"expires":1598714269892},"title":"none"},"pet":{},"team":"","achivements":[],"codesUsed":[],"nextVoteTime":0,"nextGemCashGoal":5000,"loan":{},"houses":[],"intellegencePoints":1,"strength":0,"defence":0,"maxHP":100,"hp":100},"741434497203175494":{"cash":0,"bank":0,"gems":0,"xp":3,"xpUntil":10,"level":0,"inventory":{},"username":"[P-tat0][-v-]","account":{"secured":false,"type":"user","daily":{"streak":-1,"previousAmt":0,"expires":1598722517640},"title":"none"},"pet":{},"team":"","achivements":[],"codesUsed":[],"nextVoteTime":0,"nextGemCashGoal":5000,"houses":[],"loan":{}},"563875961221677057":{"cash":0,"bank":0,"gems":0,"xp":5,"xpUntil":10,"level":0,"inventory":{},"username":"Stantheman66","account":{"secured":false,"type":"user","daily":{"streak":-1,"previousAmt":0,"expires":1598815318622},"title":"none"},"pet":{},"houses":[],"team":"","achivements":[],"codesUsed":[],"nextVoteTime":0,"nextGemCashGoal":5000,"loan":{}},"707303417437093888":{"cash":0,"bank":0,"gems":0,"xp":1,"xpUntil":10,"level":0,"inventory":{},"username":"OC_JOJO","account":{"secured":false,"type":"user","daily":{"streak":-1,"previousAmt":0,"expires":1599004570517},"title":"none"},"pet":{},"houses":[],"team":"","achivements":[],"codesUsed":[],"nextVoteTime":0,"loan":{},"nextGemCashGoal":5000},"749843887652339792":{"cash":0,"bank":0,"gems":0,"xp":2,"xpUntil":10,"level":0,"inventory":{},"username":"yayaayay","account":{"secured":false,"type":"user","daily":{"streak":-1,"previousAmt":0,"expires":1599020105227},"title":"none"},"pet":{},"houses":[],"team":"","achivements":[],"codesUsed":[],"nextVoteTime":0,"loan":{},"nextGemCashGoal":5000},"571778238280499233":{"cash":89,"bank":0,"gems":3,"xp":7,"xpUntil":40,"level":3,"inventory":{},"username":"KAYRAHAN","account":{"secured":false,"type":"user","daily":{"streak":-1,"previousAmt":0,"expires":1599395266565},"title":"none"},"pet":{},"houses":[],"team":"","achivements":[],"codesUsed":[],"nextVoteTime":0,"loan":{},"nextGemCashGoal":5000,"intellegencePoints":1,"strength":0,"defence":0,"maxHP":100,"hp":100},"727327860380925994":{"cash":2,"bank":0,"gems":1,"xp":1,"xpUntil":15,"level":1,"inventory":{},"username":"Mysterious RAT","account":{"secured":false,"type":"user","daily":{"streak":-1,"previousAmt":0,"expires":1599690727904},"title":"none"},"pet":{},"houses":[],"team":"","achivements":[],"codesUsed":[],"nextVoteTime":0,"loan":{},"intellegencePoints":1,"nextGemCashGoal":5000},"715827125999108146":{"cash":417,"bank":0,"gems":4,"xp":57,"xpUntil":60,"level":4,"inventory":{},"username":"a son","account":{"secured":false,"type":"user","daily":{"streak":-1,"previousAmt":0,"expires":1599781508295},"title":"none"},"pet":{},"houses":[],"team":"","achivements":[],"codesUsed":[],"nextVoteTime":0,"loan":{},"intellegencePoints":1,"nextGemCashGoal":5000,"strength":0,"defence":0,"maxHP":100,"hp":100},"686776377814548490":{"cash":7315,"bank":0,"gems":11,"xp":108,"xpUntil":285,"level":10,"inventory":{},"username":"Blazemech","account":{"secured":false,"type":"user","daily":{"streak":-1,"previousAmt":0,"expires":1599786132452},"title":"none"},"pet":{},"houses":[],"team":"","achivements":[],"codesUsed":[],"nextVoteTime":0,"loan":{},"intellegencePoints":1,"nextGemCashGoal":15001,"strength":0,"defence":0,"maxHP":100,"hp":100},"715459405658718249":{"cash":205,"bank":0,"gems":4,"xp":4,"xpUntil":60,"level":4,"inventory":{},"username":"HERMES","account":{"secured":false,"type":"user","daily":{"streak":-1,"previousAmt":0,"expires":1599795593998},"title":"none"},"pet":{},"houses":[],"team":"","achivements":[],"codesUsed":[],"nextVoteTime":0,"loan":{},"intellegencePoints":1,"nextGemCashGoal":5000,"strength":0,"defence":0,"maxHP":100,"hp":100},"636861946053918761":{"cash":2492,"bank":0,"gems":7,"xp":135,"xpUntil":150,"level":7,"inventory":{},"username":"FPKG","account":{"secured":false,"type":"user","daily":{"streak":-1,"previousAmt":0,"expires":1599802691537},"title":"none"},"pet":{},"houses":[],"team":"","achivements":[],"codesUsed":[],"nextVoteTime":0,"loan":{},"intellegencePoints":1,"nextGemCashGoal":5000,"strength":0,"defence":0,"maxHP":100,"hp":100},"712854224467132417":{"cash":4632,"bank":0,"gems":9,"xp":57,"xpUntil":235,"level":9,"inventory":{},"username":"Mechawave","account":{"secured":false,"type":"user","daily":{"streak":-1,"previousAmt":0,"expires":1599804625983},"title":"none"},"pet":{},"houses":[],"team":"","achivements":[],"codesUsed":[],"nextVoteTime":0,"loan":{},"intellegencePoints":1,"nextGemCashGoal":5000,"strength":0,"defence":0,"maxHP":100,"hp":100},"750522613645836369":{"cash":0,"bank":0,"gems":0,"xp":1,"xpUntil":10,"level":0,"inventory":{},"username":"You Calling Me?","account":{"secured":false,"type":"user","daily":{"streak":-1,"previousAmt":0,"expires":1599806896921},"title":"none"},"pet":{},"houses":[],"team":"","achivements":[],"codesUsed":[],"nextVoteTime":0,"loan":{},"intellegencePoints":1,"nextGemCashGoal":5000},"746455498051813479":{"cash":10,"bank":0,"gems":1,"xp":9,"xpUntil":15,"level":1,"inventory":{},"username":"PotatoCat*._.*","account":{"secured":false,"type":"user","daily":{"streak":-1,"previousAmt":0,"expires":1599869404823},"title":"none"},"pet":{},"houses":[],"team":"","achivements":[],"codesUsed":[],"nextVoteTime":0,"loan":{},"intellegencePoints":1,"nextGemCashGoal":5000,"strength":0,"defence":0,"maxHP":100,"hp":100},"745905143031267378":{"cash":0,"bank":0,"gems":0,"xp":1,"xpUntil":10,"level":0,"inventory":{},"username":"almondho","account":{"secured":false,"type":"user","daily":{"streak":-1,"previousAmt":0,"expires":1599986466576},"title":"none"},"pet":{},"houses":[],"team":"","achivements":[],"codesUsed":[],"nextVoteTime":0,"loan":{},"intellegencePoints":1,"nextGemCashGoal":5000},"679546158607237146":{"cash":7,"bank":0,"gems":1,"xp":6,"xpUntil":15,"level":1,"inventory":{},"username":"Hacker837progod","account":{"secured":false,"type":"user","daily":{"streak":-1,"previousAmt":0,"expires":1600152530725},"title":"none"},"pet":{},"houses":[],"team":"","achivements":[],"codesUsed":[],"nextVoteTime":0,"loan":{},"intellegencePoints":1,"strength":0,"defence":0,"hp":100,"maxHP":100,"nextGemCashGoal":5000},"422505993998696459":{"cash":0,"bank":0,"gems":0,"xp":1,"xpUntil":10,"level":0,"inventory":{},"username":"Zenom","account":{"secured":false,"type":"user","daily":{"streak":-1,"previousAmt":0,"expires":1600283147483},"title":"none"},"pet":{},"houses":[],"team":"","achivements":[],"codesUsed":[],"nextVoteTime":0,"loan":{},"intellegencePoints":1,"strength":0,"defence":0,"hp":100,"maxHP":100,"nextGemCashGoal":5000},"717044091074117642":{"cash":0,"bank":0,"gems":0,"xp":2,"xpUntil":10,"level":0,"inventory":{},"username":"LuhPeaxful","account":{"secured":false,"type":"user","daily":{"streak":-1,"previousAmt":0,"expires":1600285886891},"title":"none"},"pet":{},"houses":[],"team":"","achivements":[],"codesUsed":[],"nextVoteTime":0,"loan":{},"intellegencePoints":1,"strength":0,"defence":0,"hp":100,"maxHP":100,"nextGemCashGoal":5000},"690304686338605468":{"cash":0,"bank":0,"gems":0,"xp":1,"xpUntil":10,"level":0,"inventory":{},"username":"* NexarX⁹⁹","account":{"secured":false,"type":"user","daily":{"streak":-1,"previousAmt":0,"expires":1600324192949},"title":"none"},"pet":{},"houses":[],"team":"","achivements":[],"codesUsed":[],"nextVoteTime":0,"loan":{},"intellegencePoints":1,"strength":0,"defence":0,"hp":100,"maxHP":100,"nextGemCashGoal":5000},"646648396085460994":{"cash":0,"bank":0,"gems":0,"xp":1,"xpUntil":10,"level":0,"inventory":{},"username":"!不々  ExEcuteR","account":{"secured":false,"type":"user","daily":{"streak":-1,"previousAmt":0,"expires":1600328048504},"title":"none"},"pet":{},"houses":[],"team":"","achivements":[],"codesUsed":[],"nextVoteTime":0,"loan":{},"intellegencePoints":1,"strength":0,"defence":0,"hp":100,"maxHP":100,"nextGemCashGoal":5000},"686617870192345128":{"cash":0,"bank":0,"gems":0,"xp":1,"xpUntil":10,"level":0,"inventory":{},"username":"! !","account":{"secured":false,"type":"user","daily":{"streak":-1,"previousAmt":0,"expires":1600340473411},"title":"none"},"pet":{},"houses":[],"team":"","achivements":[],"codesUsed":[],"nextVoteTime":0,"loan":{},"intellegencePoints":1,"strength":0,"defence":0,"hp":100,"maxHP":100,"nextGemCashGoal":5000},"623601940559036456":{"cash":0,"bank":0,"gems":0,"xp":1,"xpUntil":10,"level":0,"inventory":{},"username":"Wood","account":{"secured":false,"type":"user","daily":{"streak":-1,"previousAmt":0,"expires":1600342505322},"title":"none"},"pet":{},"houses":[],"team":"","achivements":[],"codesUsed":[],"nextVoteTime":0,"loan":{},"intellegencePoints":1,"strength":0,"defence":0,"hp":100,"maxHP":100,"nextGemCashGoal":5000},"338598671895494657":{"cash":0,"bank":0,"gems":0,"xp":2,"xpUntil":10,"level":0,"inventory":{},"username":"⍭ Taco*𝖙𝖕","account":{"secured":false,"type":"user","daily":{"streak":-1,"previousAmt":0,"expires":1600366241832},"title":"none"},"pet":{},"houses":[],"team":"","achivements":[],"codesUsed":[],"nextVoteTime":0,"loan":{},"intellegencePoints":1,"strength":0,"defence":0,"hp":100,"maxHP":100,"nextGemCashGoal":5000},"454727578125860866":{"cash":0,"bank":0,"gems":0,"xp":4,"xpUntil":10,"level":0,"inventory":{},"username":"JustCay","account":{"secured":false,"type":"user","daily":{"streak":-1,"previousAmt":0,"expires":1600400241140},"title":"none"},"pet":{},"houses":[],"team":"","achivements":[],"codesUsed":[],"nextVoteTime":0,"loan":{},"intellegencePoints":1,"strength":0,"defence":0,"hp":100,"maxHP":100,"nextGemCashGoal":5000},"529143812464050186":{"cash":0,"bank":0,"gems":0,"xp":1,"xpUntil":10,"level":0,"inventory":{},"username":"\"i had fun once, it was awful\"","account":{"secured":false,"type":"user","daily":{"streak":-1,"previousAmt":0,"expires":1600400846511},"title":"none"},"pet":{},"houses":[],"team":"","achivements":[],"codesUsed":[],"nextVoteTime":0,"loan":{},"intellegencePoints":1,"strength":0,"defence":0,"hp":100,"maxHP":100,"nextGemCashGoal":5000},"719810339633496105":{"cash":0,"bank":0,"gems":0,"xp":5,"xpUntil":10,"level":0,"inventory":{},"username":"Eddie Zhang","account":{"secured":false,"type":"user","daily":{"streak":-1,"previousAmt":0,"expires":1600408612388},"title":"none"},"pet":{},"houses":[],"team":"","achivements":[],"codesUsed":[],"nextVoteTime":0,"loan":{},"intellegencePoints":1,"strength":0,"defence":0,"hp":100,"maxHP":100,"nextGemCashGoal":5000},"447480379092500482":{"cash":0,"bank":0,"gems":0,"xp":1,"xpUntil":10,"level":0,"inventory":{},"username":"✧Gladius","account":{"secured":false,"type":"user","daily":{"streak":-1,"previousAmt":0,"expires":1600411328708},"title":"none"},"pet":{},"houses":[],"team":"","achivements":[],"codesUsed":[],"nextVoteTime":0,"loan":{},"intellegencePoints":1,"strength":0,"defence":0,"hp":100,"maxHP":100,"nextGemCashGoal":5000},"479581834389356560":{"cash":0,"bank":0,"gems":0,"xp":1,"xpUntil":10,"level":0,"inventory":{},"username":"✵ALPEREN⁸⁸⁰","account":{"secured":false,"type":"user","daily":{"streak":-1,"previousAmt":0,"expires":1600417054591},"title":"none"},"pet":{},"houses":[],"team":"","achivements":[],"codesUsed":[],"nextVoteTime":0,"loan":{},"intellegencePoints":1,"strength":0,"defence":0,"hp":100,"maxHP":100,"nextGemCashGoal":5000},"717590986116694056":{"cash":0,"bank":0,"gems":0,"xp":2,"xpUntil":10,"level":0,"inventory":{},"username":"Elma Bot Is But Sad","account":{"secured":false,"type":"user","daily":{"streak":-1,"previousAmt":0,"expires":1600435218772},"title":"none"},"pet":{},"houses":[],"team":"","achivements":[],"codesUsed":[],"nextVoteTime":0,"loan":{},"intellegencePoints":1,"strength":0,"defence":0,"hp":100,"maxHP":100,"nextGemCashGoal":5000},"738309598842454068":{"cash":0,"bank":0,"gems":0,"xp":2,"xpUntil":10,"level":0,"inventory":{},"username":"➴ AET `E","account":{"secured":false,"type":"user","daily":{"streak":-1,"previousAmt":0,"expires":1600435416220},"title":"none"},"pet":{},"houses":[],"team":"","achivements":[],"codesUsed":[],"nextVoteTime":0,"loan":{},"intellegencePoints":1,"strength":0,"defence":0,"hp":100,"maxHP":100,"nextGemCashGoal":5000},"729990136619728946":{"cash":0,"bank":0,"gems":0,"xp":1,"xpUntil":10,"level":0,"inventory":{},"username":"†                HzShadow","account":{"secured":false,"type":"user","daily":{"streak":-1,"previousAmt":0,"expires":1600437254333},"title":"none"},"pet":{},"houses":[],"team":"","achivements":[],"codesUsed":[],"nextVoteTime":0,"loan":{},"intellegencePoints":1,"strength":0,"defence":0,"hp":100,"maxHP":100,"nextGemCashGoal":5000},"423533578518003722":{"cash":0,"bank":0,"gems":0,"xp":1,"xpUntil":10,"level":0,"inventory":{},"username":"!             Enes","account":{"secured":false,"type":"user","daily":{"streak":-1,"previousAmt":0,"expires":1600456992653},"title":"none"},"pet":{},"houses":[],"team":"","achivements":[],"codesUsed":[],"nextVoteTime":0,"loan":{},"intellegencePoints":1,"strength":0,"defence":0,"hp":100,"maxHP":100,"nextGemCashGoal":5000},"503985776414162944":{"cash":0,"bank":0,"gems":0,"xp":3,"xpUntil":10,"level":0,"inventory":{},"username":"Anz","account":{"secured":false,"type":"user","daily":{"streak":-1,"previousAmt":0,"expires":1600457561496},"title":"none"},"pet":{},"houses":[],"team":"","achivements":[],"codesUsed":[],"nextVoteTime":0,"loan":{},"intellegencePoints":1,"strength":0,"defence":0,"hp":100,"maxHP":100,"nextGemCashGoal":5000},"691020792749883432":{"cash":0,"bank":0,"gems":0,"xp":3,"xpUntil":10,"level":0,"inventory":{},"username":"Dwarf","account":{"secured":false,"type":"user","daily":{"streak":-1,"previousAmt":0,"expires":1600465406079},"title":"none"},"pet":{},"houses":[],"team":"","achivements":[],"codesUsed":[],"nextVoteTime":0,"loan":{},"intellegencePoints":1,"strength":0,"defence":0,"hp":100,"maxHP":100,"nextGemCashGoal":5000},"700018229443297281":{"cash":0,"bank":0,"gems":0,"xp":1,"xpUntil":10,"level":0,"inventory":{},"username":"Ѫ FAΖLI🎈","account":{"secured":false,"type":"user","daily":{"streak":-1,"previousAmt":0,"expires":1600465704792},"title":"none"},"pet":{},"houses":[],"team":"","achivements":[],"codesUsed":[],"nextVoteTime":0,"loan":{},"intellegencePoints":1,"strength":0,"defence":0,"hp":100,"maxHP":100,"nextGemCashGoal":5000},"536586783870156820":{"cash":0,"bank":0,"gems":0,"xp":1,"xpUntil":10,"level":0,"inventory":{},"username":"! DarkNem","account":{"secured":false,"type":"user","daily":{"streak":-1,"previousAmt":0,"expires":1600466076607},"title":"none"},"pet":{},"houses":[],"team":"","achivements":[],"codesUsed":[],"nextVoteTime":0,"loan":{},"intellegencePoints":1,"strength":0,"defence":0,"hp":100,"maxHP":100,"nextGemCashGoal":5000},"707306670824357979":{"cash":0,"bank":0,"gems":0,"xp":1,"xpUntil":10,"level":0,"inventory":{},"username":"`ℭ Mr.Alpha","account":{"secured":false,"type":"user","daily":{"streak":-1,"previousAmt":0,"expires":1600466249746},"title":"none"},"pet":{},"houses":[],"team":"","achivements":[],"codesUsed":[],"nextVoteTime":0,"loan":{},"intellegencePoints":1,"strength":0,"defence":0,"hp":100,"maxHP":100,"nextGemCashGoal":5000},"386601127929708545":{"cash":0,"bank":0,"gems":0,"xp":1,"xpUntil":10,"level":0,"inventory":{},"username":"么KewP","account":{"secured":false,"type":"user","daily":{"streak":-1,"previousAmt":0,"expires":1600466273677},"title":"none"},"pet":{},"houses":[],"team":"","achivements":[],"codesUsed":[],"nextVoteTime":0,"loan":{},"intellegencePoints":1,"strength":0,"defence":0,"hp":100,"maxHP":100,"nextGemCashGoal":5000},"750443840657162421":{"cash":0,"bank":0,"gems":0,"xp":1,"xpUntil":10,"level":0,"inventory":{},"username":"Verâ Bot Geliştirici","account":{"secured":false,"type":"user","daily":{"streak":-1,"previousAmt":0,"expires":1600471308004},"title":"none"},"pet":{},"houses":[],"team":"","achivements":[],"codesUsed":[],"nextVoteTime":0,"loan":{},"intellegencePoints":1,"strength":0,"defence":0,"hp":100,"maxHP":100,"nextGemCashGoal":5000},"693559583909871666":{"cash":0,"bank":0,"gems":0,"xp":1,"xpUntil":10,"level":0,"inventory":{},"username":"₪ | ! I̷mCreewl.404","account":{"secured":false,"type":"user","daily":{"streak":-1,"previousAmt":0,"expires":1600471542167},"title":"none"},"pet":{},"houses":[],"team":"","achivements":[],"codesUsed":[],"nextVoteTime":0,"loan":{},"intellegencePoints":1,"strength":0,"defence":0,"hp":100,"maxHP":100,"nextGemCashGoal":5000},"536545688721293332":{"cash":0,"bank":0,"gems":0,"xp":1,"xpUntil":10,"level":0,"inventory":{},"username":"! Miraç ARSLAN⁸⁸⁰","account":{"secured":false,"type":"user","daily":{"streak":-1,"previousAmt":0,"expires":1600486050637},"title":"none"},"pet":{},"houses":[],"team":"","achivements":[],"codesUsed":[],"nextVoteTime":0,"loan":{},"intellegencePoints":1,"strength":0,"defence":0,"hp":100,"maxHP":100,"nextGemCashGoal":5000},"427014078230167554":{"cash":0,"bank":0,"gems":0,"xp":1,"xpUntil":10,"level":0,"inventory":{},"username":"Lasty","account":{"secured":false,"type":"user","daily":{"streak":-1,"previousAmt":0,"expires":1600499898395},"title":"none"},"pet":{},"houses":[],"team":"","achivements":[],"codesUsed":[],"nextVoteTime":0,"loan":{},"intellegencePoints":1,"strength":0,"defence":0,"hp":100,"maxHP":100,"nextGemCashGoal":5000},"640415975937671168":{"cash":0,"bank":0,"gems":0,"xp":3,"xpUntil":10,"level":0,"inventory":{},"username":"Experio","account":{"secured":false,"type":"user","daily":{"streak":-1,"previousAmt":0,"expires":1600501685627},"title":"none"},"pet":{},"houses":[],"team":"","achivements":[],"codesUsed":[],"nextVoteTime":0,"loan":{},"intellegencePoints":1,"strength":0,"defence":0,"hp":100,"maxHP":100,"nextGemCashGoal":5000},"666306498594471938":{"cash":0,"bank":0,"gems":0,"xp":1,"xpUntil":10,"level":0,"inventory":{},"username":"R.EKREM","account":{"secured":false,"type":"user","daily":{"streak":-1,"previousAmt":0,"expires":1600501836682},"title":"none"},"pet":{},"houses":[],"team":"","achivements":[],"codesUsed":[],"nextVoteTime":0,"loan":{},"intellegencePoints":1,"strength":0,"defence":0,"hp":100,"maxHP":100,"nextGemCashGoal":5000},"646425400498585603":{"cash":0,"bank":0,"gems":0,"xp":1,"xpUntil":10,"level":0,"inventory":{},"username":"Heja","account":{"secured":false,"type":"user","daily":{"streak":-1,"previousAmt":0,"expires":1600513236770},"title":"none"},"pet":{},"houses":[],"team":"","achivements":[],"codesUsed":[],"nextVoteTime":0,"loan":{},"intellegencePoints":1,"strength":0,"defence":0,"hp":100,"maxHP":100,"nextGemCashGoal":5000},"419363424733102080":{"cash":0,"bank":0,"gems":0,"xp":1,"xpUntil":10,"level":0,"inventory":{},"username":"⍭ nickneymos","account":{"secured":false,"type":"user","daily":{"streak":-1,"previousAmt":0,"expires":1600514551512},"title":"none"},"pet":{},"houses":[],"team":"","achivements":[],"codesUsed":[],"nextVoteTime":0,"loan":{},"intellegencePoints":1,"strength":0,"defence":0,"hp":100,"maxHP":100,"nextGemCashGoal":5000},"755335799989600276":{"cash":0,"bank":0,"gems":0,"xp":1,"xpUntil":10,"level":0,"inventory":{},"username":"PeskyBird","account":{"secured":false,"type":"user","daily":{"streak":-1,"previousAmt":0,"expires":1600523681734},"title":"none"},"pet":{},"houses":[],"team":"","achivements":[],"codesUsed":[],"nextVoteTime":0,"loan":{},"intellegencePoints":1,"strength":0,"defence":0,"hp":100,"maxHP":100,"nextGemCashGoal":5000},"730517418559930458":{"cash":0,"bank":0,"gems":0,"xp":2,"xpUntil":10,"level":0,"inventory":{},"username":"`Wéarlés","account":{"secured":false,"type":"user","daily":{"streak":-1,"previousAmt":0,"expires":1600525556609},"title":"none"},"pet":{},"houses":[],"team":"","achivements":[],"codesUsed":[],"nextVoteTime":0,"loan":{},"intellegencePoints":1,"strength":0,"defence":0,"hp":100,"maxHP":100,"nextGemCashGoal":5000},"751540856573395046":{"cash":0,"bank":0,"gems":0,"xp":1,"xpUntil":10,"level":0,"inventory":{},"username":"ErenxSad","account":{"secured":false,"type":"user","daily":{"streak":-1,"previousAmt":0,"expires":1600549945747},"title":"none"},"pet":{},"houses":[],"team":"","achivements":[],"codesUsed":[],"nextVoteTime":0,"loan":{},"intellegencePoints":1,"strength":0,"defence":0,"hp":100,"maxHP":100,"nextGemCashGoal":5000},"523145984138805250":{"cash":0,"bank":0,"gems":0,"xp":2,"xpUntil":10,"level":0,"inventory":{},"username":"⌔ Ben Aral","account":{"secured":false,"type":"user","daily":{"streak":-1,"previousAmt":0,"expires":1600571092815},"title":"none"},"pet":{},"houses":[],"team":"","achivements":[],"codesUsed":[],"nextVoteTime":0,"loan":{},"intellegencePoints":1,"strength":0,"defence":0,"hp":100,"maxHP":100,"nextGemCashGoal":5000},"705025627014824026":{"cash":0,"bank":0,"gems":0,"xp":1,"xpUntil":10,"level":0,"inventory":{},"username":"Gokoscope🌙","account":{"secured":false,"type":"user","daily":{"streak":-1,"previousAmt":0,"expires":1600592482029},"title":"none"},"pet":{},"houses":[],"team":"","achivements":[],"codesUsed":[],"nextVoteTime":0,"loan":{},"intellegencePoints":1,"strength":0,"defence":0,"hp":100,"maxHP":100,"nextGemCashGoal":5000},"603649798696075264":{"cash":0,"bank":0,"gems":0,"xp":1,"xpUntil":10,"level":0,"inventory":{},"username":"YOKEDER","account":{"secured":false,"type":"user","daily":{"streak":-1,"previousAmt":0,"expires":1600595480731},"title":"none"},"pet":{},"houses":[],"team":"","achivements":[],"codesUsed":[],"nextVoteTime":0,"loan":{},"intellegencePoints":1,"strength":0,"defence":0,"hp":100,"maxHP":100,"nextGemCashGoal":5000},"660446983445676032":{"cash":0,"bank":0,"gems":0,"xp":1,"xpUntil":10,"level":0,"inventory":{},"username":"Ξ U R O","account":{"secured":false,"type":"user","daily":{"streak":-1,"previousAmt":0,"expires":1600597970341},"title":"none"},"pet":{},"houses":[],"team":"","achivements":[],"codesUsed":[],"nextVoteTime":0,"loan":{},"intellegencePoints":1,"strength":0,"defence":0,"hp":100,"maxHP":100,"nextGemCashGoal":5000},"533003187989250060":{"cash":0,"bank":0,"gems":0,"xp":1,"xpUntil":10,"level":0,"inventory":{},"username":"09ahmetK","account":{"secured":false,"type":"user","daily":{"streak":-1,"previousAmt":0,"expires":1600602611124},"title":"none"},"pet":{},"houses":[],"team":"","achivements":[],"codesUsed":[],"nextVoteTime":0,"loan":{},"intellegencePoints":1,"strength":0,"defence":0,"hp":100,"maxHP":100,"nextGemCashGoal":5000},"753950404668162158":{"cash":0,"bank":0,"gems":0,"xp":1,"xpUntil":10,"level":0,"inventory":{},"username":"Jawe`X","account":{"secured":false,"type":"user","daily":{"streak":-1,"previousAmt":0,"expires":1600620906697},"title":"none"},"pet":{},"houses":[],"team":"","achivements":[],"codesUsed":[],"nextVoteTime":0,"loan":{},"intellegencePoints":1,"strength":0,"defence":0,"hp":100,"maxHP":100,"nextGemCashGoal":5000},"340565382609764352":{"cash":0,"bank":0,"gems":0,"xp":1,"xpUntil":10,"level":0,"inventory":{},"username":"Drâknost","account":{"secured":false,"type":"user","daily":{"streak":-1,"previousAmt":0,"expires":1600624091804},"title":"none"},"pet":{},"houses":[],"team":"","achivements":[],"codesUsed":[],"nextVoteTime":0,"loan":{},"intellegencePoints":1,"strength":0,"defence":0,"hp":100,"maxHP":100,"nextGemCashGoal":5000},"380725854646566912":{"cash":0,"bank":0,"gems":0,"xp":1,"xpUntil":10,"level":0,"inventory":{},"username":"Osman 19","account":{"secured":false,"type":"user","daily":{"streak":-1,"previousAmt":0,"expires":1600627459555},"title":"none"},"pet":{},"houses":[],"team":"","achivements":[],"codesUsed":[],"nextVoteTime":0,"loan":{},"intellegencePoints":1,"strength":0,"defence":0,"hp":100,"maxHP":100,"nextGemCashGoal":5000},"398847060100644864":{"cash":0,"bank":0,"gems":0,"xp":1,"xpUntil":10,"level":0,"inventory":{},"username":"็็🌙","account":{"secured":false,"type":"user","daily":{"streak":-1,"previousAmt":0,"expires":1600628014389},"title":"none"},"pet":{},"houses":[],"team":"","achivements":[],"codesUsed":[],"nextVoteTime":0,"loan":{},"intellegencePoints":1,"strength":0,"defence":0,"hp":100,"maxHP":100,"nextGemCashGoal":5000},"392365595976400898":{"cash":0,"bank":0,"gems":0,"xp":1,"xpUntil":10,"level":0,"inventory":{},"username":"Yiğit 🌙","account":{"secured":false,"type":"user","daily":{"streak":-1,"previousAmt":0,"expires":1600640383634},"title":"none"},"pet":{},"houses":[],"team":"","achivements":[],"codesUsed":[],"nextVoteTime":0,"loan":{},"intellegencePoints":1,"strength":0,"defence":0,"hp":100,"maxHP":100,"nextGemCashGoal":5000},"623167228140978218":{"cash":0,"bank":0,"gems":0,"xp":1,"xpUntil":10,"level":0,"inventory":{},"username":"⁰ ⁰ ⁵! ᴍüᴘᴛᴇʟᴀ 〝Erenɪᴢᴍ?","account":{"secured":false,"type":"user","daily":{"streak":-1,"previousAmt":0,"expires":1600641812453},"title":"none"},"pet":{},"houses":[],"team":"","achivements":[],"codesUsed":[],"nextVoteTime":0,"loan":{},"intellegencePoints":1,"strength":0,"defence":0,"hp":100,"maxHP":100,"nextGemCashGoal":5000},"716903456278970428":{"cash":0,"bank":0,"gems":0,"xp":1,"xpUntil":10,"level":0,"inventory":{},"username":"skankhunt42","account":{"secured":false,"type":"user","daily":{"streak":-1,"previousAmt":0,"expires":1600678610183},"title":"none"},"pet":{},"houses":[],"team":"","achivements":[],"codesUsed":[],"nextVoteTime":0,"loan":{},"intellegencePoints":1,"strength":0,"defence":0,"hp":100,"maxHP":100,"nextGemCashGoal":5000},"749966727881687070":{"cash":0,"bank":0,"gems":0,"xp":1,"xpUntil":10,"level":0,"inventory":{},"username":"✮亗 Œ Ñ Ū R そを","account":{"secured":false,"type":"user","daily":{"streak":-1,"previousAmt":0,"expires":1600684815201},"title":"none"},"pet":{},"houses":[],"team":"","achivements":[],"codesUsed":[],"nextVoteTime":0,"loan":{},"intellegencePoints":1,"strength":0,"defence":0,"hp":100,"maxHP":100,"nextGemCashGoal":5000},"381277806514143254":{"cash":0,"bank":0,"gems":0,"xp":5,"xpUntil":10,"level":0,"inventory":{},"username":"just bao","account":{"secured":false,"type":"user","daily":{"streak":-1,"previousAmt":0,"expires":1600729078292},"title":"none"},"pet":{},"houses":[],"team":"","achivements":[],"codesUsed":[],"nextVoteTime":0,"loan":{},"intellegencePoints":1,"strength":0,"defence":0,"hp":100,"maxHP":100,"nextGemCashGoal":5000},"630294811198619651":{"cash":0,"bank":0,"gems":0,"xp":1,"xpUntil":10,"level":0,"inventory":{},"username":"!  ꧁~■☬𝕮𝕬𝕶𝕴𝕽☬■~꧂ッ","account":{"secured":false,"type":"user","daily":{"streak":-1,"previousAmt":0,"expires":1600755635406},"title":"none"},"pet":{},"houses":[],"team":"","achivements":[],"codesUsed":[],"nextVoteTime":0,"loan":{},"intellegencePoints":1,"strength":0,"defence":0,"hp":100,"maxHP":100,"nextGemCashGoal":5000},"320672609647853578":{"cash":0,"bank":0,"gems":0,"xp":1,"xpUntil":10,"level":0,"inventory":{},"username":"✵ Clowˢᵗᵉᵖ","account":{"secured":false,"type":"user","daily":{"streak":-1,"previousAmt":0,"expires":1600764638255},"title":"none"},"pet":{},"houses":[],"team":"","achivements":[],"codesUsed":[],"nextVoteTime":0,"loan":{},"intellegencePoints":1,"strength":0,"defence":0,"hp":100,"maxHP":100,"nextGemCashGoal":5000},"403952711617347604":{"cash":0,"bank":0,"gems":0,"xp":1,"xpUntil":10,"level":0,"inventory":{},"username":"Bay İlbeycik","account":{"secured":false,"type":"user","daily":{"streak":-1,"previousAmt":0,"expires":1600790155469},"title":"none"},"pet":{},"houses":[],"team":"","achivements":[],"codesUsed":[],"nextVoteTime":0,"loan":{},"intellegencePoints":1,"strength":0,"defence":0,"hp":100,"maxHP":100,"nextGemCashGoal":5000}}